[
    {
        "id": "208e13f2-7609-4d5c-832e-71fa75319c22",
        "enable": true,
        "name": "DonchianBreakoutClassicLongDaily",
        "description": "Пробой границы канала Дончиана. Выход по трейлинг-стопу по противоположной границе",
        "timeframe": "D",
        "tickerList": "algo/shares",
        "params": [
            { "name": "PeriodEntry", "default": 10, "min": 10, "max": 50, "step": 5 },
            { "name": "PeriodExit", "default": 10, "min": 10, "max": 50, "step": 5 }
        ]
    }
]